e2eAIOK/__init__.py
e2eAIOK/version
e2eAIOK/SDA/SDA.py
e2eAIOK/SDA/__init__.py
e2eAIOK/SDA/modeladvisor/BERTAdvisor.py
e2eAIOK/SDA/modeladvisor/BaseModelAdvisor.py
e2eAIOK/SDA/modeladvisor/DIENAdvisor.py
e2eAIOK/SDA/modeladvisor/DLRMAdvisor.py
e2eAIOK/SDA/modeladvisor/MiniGoAdvisor.py
e2eAIOK/SDA/modeladvisor/RNNTAdvisor.py
e2eAIOK/SDA/modeladvisor/RegisteredAdvisor.py
e2eAIOK/SDA/modeladvisor/ResNetAdvisor.py
e2eAIOK/SDA/modeladvisor/TestAdvisor.py
e2eAIOK/SDA/modeladvisor/TwitterRecSysAdvisor.py
e2eAIOK/SDA/modeladvisor/UPMAdvisor.py
e2eAIOK/SDA/modeladvisor/WnDAdvisor.py
e2eAIOK/SDA/modeladvisor/__init__.py
e2eAIOK/common/__init__.py
e2eAIOK/common/default.conf
e2eAIOK/common/utils.py
e2eAIOK/common/trainer/__init__.py
e2eAIOK/common/trainer/data_builder.py
e2eAIOK/common/trainer/model_builder.py
e2eAIOK/common/trainer/torch_trainer.py
e2eAIOK/common/trainer/data/__init__.py
e2eAIOK/common/trainer/data/data_builder_asr.py
e2eAIOK/common/trainer/data/data_builder_cv.py
e2eAIOK/common/trainer/data/data_builder_nlp.py
e2eAIOK/common/trainer/data/asr/__init__.py
e2eAIOK/common/trainer/data/asr/data_builder_librispeech.py
e2eAIOK/common/trainer/data/cv/__init__.py
e2eAIOK/common/trainer/data/cv/data_builder_cifar.py
e2eAIOK/common/trainer/data/cv/data_builder_imagenet.py
e2eAIOK/common/trainer/data/cv/data_builder_uspsvsminist.py
e2eAIOK/common/trainer/data/data_utils/__init__.py
e2eAIOK/common/trainer/data/data_utils/data_utils.py
e2eAIOK/common/trainer/data/data_utils/image_list.py
e2eAIOK/common/trainer/data/data_utils/loader.py
e2eAIOK/common/trainer/data/nlp/__init__.py
e2eAIOK/common/trainer/data/nlp/data_builder_squad.py
e2eAIOK/common/trainer/model/__init__.py
e2eAIOK/common/trainer/model/model_builder_asr.py
e2eAIOK/common/trainer/model/model_builder_cv.py
e2eAIOK/common/trainer/model/model_builder_nlp.py
e2eAIOK/common/trainer/model/cv/__init__.py
e2eAIOK/common/trainer/model/cv/lenet.py
e2eAIOK/common/trainer/model/cv/resnet_cifar.py
e2eAIOK_sda-1.1.0.dist-info/LICENSE
e2eAIOK_sda-1.1.0.dist-info/METADATA
e2eAIOK_sda-1.1.0.dist-info/WHEEL
e2eAIOK_sda-1.1.0.dist-info/top_level.txt
e2eAIOK_sda-1.1.0.dist-info/RECORD
